pelican/plugins/compressor/__init__.py
pelican_compressor-0.2.1.dist-info/LICENSE
pelican_compressor-0.2.1.dist-info/WHEEL
pelican_compressor-0.2.1.dist-info/METADATA
pelican_compressor-0.2.1.dist-info/RECORD
